snompy/__init__.py
snompy/_defaults.py
snompy/_utils.py
snompy/_version.py
snompy/demodulate.py
snompy/fdm.py
snompy/pdm.py
snompy/sample.py
snompy-0.1.9.dist-info/LICENCE.txt
snompy-0.1.9.dist-info/METADATA
snompy-0.1.9.dist-info/WHEEL
snompy-0.1.9.dist-info/top_level.txt
snompy-0.1.9.dist-info/RECORD
