Metadata-Version: 2.1
Name: snompy
Version: 0.1.9
Summary: A Python package for modelling scanning near-field optical microscopy measurements.
Author: Tom Vincent
Author-email: TomVincentCode@gmail.com
Classifier: Programming Language :: Python :: 3
Classifier: Operating System :: OS Independent
Classifier: License :: OSI Approved :: MIT License
Requires-Python: >=3.10
License-File: LICENCE.txt
Requires-Dist: numpy
